Workbook

Sheet تراکنش‌ها
A1: تاریخ | B1: نوع | C1: دسته‌بندی | D1: شرح | E1: مبلغ
A2: 46025 | B2: Income | C2: Sales | D2: Sales revenue | E2: 3200
A3: 46032 | B3: Expense | C3: Marketing | D3: Marketing expense | E3: 445
A4: 46039 | B4: Expense | C4: Utilities | D4: Utilities expense | E4: 540
A5: 46046 | B5: Income | C5: Consulting | D5: Consulting revenue | E5: 4250
A6: 46053 | B6: Expense | C6: Transport | D6: Transport expense | E6: 730
A7: 46060 | B7: Expense | C7: Office | D7: Office expense | E7: 825
A8: 46067 | B8: Income | C8: Services | D8: Services revenue | E8: 5300
A9: 46074 | B9: Expense | C9: Marketing | D9: Marketing expense | E9: 1015
A10: 46081 | B10: Expense | C10: Utilities | D10: Utilities expense | E10: 350
A11: 46088 | B11: Income | C11: Sales | D11: Sales revenue | E11: 3900
A12: 46095 | B12: Expense | C12: Transport | D12: Transport expense | E12: 540
A13: 46102 | B13: Expense | C13: Office | D13: Office expense | E13: 635
... A49: 46354 | B49: Expense | C49: Office | D49: Office expense | E49: 1015

Sheet بودجه
A1: دسته‌بندی | B1: بودجه سالانه | C1: هزینه واقعی | D1: انحراف بودجه
A2: Rent | B2: 7200 | C2: =SUMIFS(تراکنش‌ها!$E$2:$E$49,تراکنش‌ها!$B$2:$B$49,"Expense",تراکنش‌ها!$C$2:$C$49,A2) -> 0 | D2: =B2-C2 -> 7200
A3: Marketing | B3: 5200 | C3: =SUMIFS(تراکنش‌ها!$E$2:$E$49,تراکنش‌ها!$B$2:$B$49,"Expense",تراکنش‌ها!$C$2:$C$49,A3) -> 5840 | D3: =B3-C3 -> -640
A4: Utilities | B4: 3600 | C4: =SUMIFS(تراکنش‌ها!$E$2:$E$49,تراکنش‌ها!$B$2:$B$49,"Expense",تراکنش‌ها!$C$2:$C$49,A4) -> 5080 | D4: =B4-C4 -> -1480
A5: Software | B5: 4200 | C5: =SUMIFS(تراکنش‌ها!$E$2:$E$49,تراکنش‌ها!$B$2:$B$49,"Expense",تراکنش‌ها!$C$2:$C$49,A5) -> 0 | D5: =B5-C5 -> 4200
A6: Transport | B6: 3000 | C6: =SUMIFS(تراکنش‌ها!$E$2:$E$49,تراکنش‌ها!$B$2:$B$49,"Expense",تراکنش‌ها!$C$2:$C$49,A6) -> 5080 | D6: =B6-C6 -> -2080
A7: Office | B7: 2600 | C7: =SUMIFS(تراکنش‌ها!$E$2:$E$49,تراکنش‌ها!$B$2:$B$49,"Expense",تراکنش‌ها!$C$2:$C$49,A7) -> 5840 | D7: =B7-C7 -> -3240

Sheet داشبورد مالی
A1: HMexcelpro | داشبورد مالی و هزینه‌ها
A4: کل درآمد | D4: کل هزینه | G4: سود خالص | J4: حاشیه سود
A5: =SUMIF(تراکنش‌ها!$B$2:$B$49,"Income",تراکنش‌ها!$E$2:$E$49) -> 66950 | D5: =SUMIF(تراکنش‌ها!$B$2:$B$49,"Expense",تراکنش‌ها!$E$2:$E$49) -> 21840 | G5: =SUMIF(تراکنش‌ها!$B$2:$B$49,"Income",تراکنش‌ها!$E$2:$E$49)-SUMIF(تراکنش‌ها!$B$2:$B$49,"Expense",تراکنش‌ها!$E$2:$E$49) -> 45110 | J5: =IFERROR((SUMIF(تراکنش‌ها!$B$2:$B$49,"Income",تراکنش‌ها!$E$2:$E$49)-SUMIF(تراکنش‌ها!$B$2:$B$49,"Expense",تراکنش‌ها!$E$2:$E$49))/SUMIF(تراکنش‌ها!$B$2:$B$49,"Income",تراکنش‌ها!$E$2:$E$49),0) -> 0.67378641
A9: ماه | B9: درآمد | C9: هزینه | E9: دسته‌بندی | F9: بودجه سالانه | G9: هزینه واقعی | H9: انحراف بودجه
A10: 46023 | B10: =SUMIFS(تراکنش‌ها!$E$2:$E$49,تراکنش‌ها!$B$2:$B$49,"Income",تراکنش‌ها!$A$2:$A$49,">="&A10,تراکنش‌ها!$A$2:$A$49,"<"&EDATE(A10,1)) -> 7450 | C10: =SUMIFS(تراکنش‌ها!$E$2:$E$49,تراکنش‌ها!$B$2:$B$49,"Expense",تراکنش‌ها!$A$2:$A$49,">="&A10,تراکنش‌ها!$A$2:$A$49,"<"&EDATE(A10,1)) -> 1715 | E10: Rent | F10: =بودجه!B2 -> 7200 | G10: =بودجه!C2 -> 0 | H10: =بودجه!D2 -> 7200
A11: 46054 | B11: =SUMIFS(تراکنش‌ها!$E$2:$E$49,تراکنش‌ها!$B$2:$B$49,"Income",تراکنش‌ها!$A$2:$A$49,">="&A11,تراکنش‌ها!$A$2:$A$49,"<"&EDATE(A11,1)) -> 5300 | C11: =SUMIFS(تراکنش‌ها!$E$2:$E$49,تراکنش‌ها!$B$2:$B$49,"Expense",تراکنش‌ها!$A$2:$A$49,">="&A11,تراکنش‌ها!$A$2:$A$49,"<"&EDATE(A11,1)) -> 2190 | E11: Marketing | F11: =بودجه!B3 -> 5200 | G11: =بودجه!C3 -> 5840 | H11: =بودجه!D3 -> -640
A12: 46082 | B12: =SUMIFS(تراکنش‌ها!$E$2:$E$49,تراکنش‌ها!$B$2:$B$49,"Income",تراکنش‌ها!$A$2:$A$49,">="&A12,تراکنش‌ها!$A$2:$A$49,"<"&EDATE(A12,1)) -> 8850 | C12: =SUMIFS(تراکنش‌ها!$E$2:$E$49,تراکنش‌ها!$B$2:$B$49,"Expense",تراکنش‌ها!$A$2:$A$49,">="&A12,تراکنش‌ها!$A$2:$A$49,"<"&EDATE(A12,1)) -> 1175 | E12: Utilities | F12: =بودجه!B4 -> 3600 | G12: =بودجه!C4 -> 5080 | H12: =بودجه!D4 -> -1480
A13: 46113 | B13: =SUMIFS(تراکنش‌ها!$E$2:$E$49,تراکنش‌ها!$B$2:$B$49,"Income",تراکنش‌ها!$A$2:$A$49,">="&A13,تراکنش‌ها!$A$2:$A$49,"<"&EDATE(A13,1)) -> 3550 | C13: =SUMIFS(تراکنش‌ها!$E$2:$E$49,تراکنش‌ها!$B$2:$B$49,"Expense",تراکنش‌ها!$A$2:$A$49,">="&A13,تراکنش‌ها!$A$2:$A$49,"<"&EDATE(A13,1)) -> 2095 | E13: Software | F13: =بودجه!B5 -> 4200 | G13: =بودجه!C5 -> 0 | H13: =بودجه!D5 -> 4200
A14: 46143 | B14: =SUMIFS(تراکنش‌ها!$E$2:$E$49,تراکنش‌ها!$B$2:$B$49,"Income",تراکنش‌ها!$A$2:$A$49,">="&A14,تراکنش‌ها!$A$2:$A$49,"<"&EDATE(A14,1)) -> 7800 | C14: =SUMIFS(تراکنش‌ها!$E$2:$E$49,تراکنش‌ها!$B$2:$B$49,"Expense",تراکنش‌ها!$A$2:$A$49,">="&A14,تراکنش‌ها!$A$2:$A$49,"<"&EDATE(A14,1)) -> 1810 | E14: Transport | F14: =بودجه!B6 -> 3000 | G14: =بودجه!C6 -> 5080 | H14: =بودجه!D6 -> -2080
A15: 46174 | B15: =SUMIFS(تراکنش‌ها!$E$2:$E$49,تراکنش‌ها!$B$2:$B$49,"Income",تراکنش‌ها!$A$2:$A$49,">="&A15,تراکنش‌ها!$A$2:$A$49,"<"&EDATE(A15,1)) -> 4250 | C15: =SUMIFS(تراکنش‌ها!$E$2:$E$49,تراکنش‌ها!$B$2:$B$49,"Expense",تراکنش‌ها!$A$2:$A$49,">="&A15,تراکنش‌ها!$A$2:$A$49,"<"&EDATE(A15,1)) -> 2380 | E15: Office | F15: =بودجه!B7 -> 2600 | G15: =بودجه!C7 -> 5840 | H15: =بودجه!D7 -> -3240
A16: 46204 | B16: =SUMIFS(تراکنش‌ها!$E$2:$E$49,تراکنش‌ها!$B$2:$B$49,"Income",تراکنش‌ها!$A$2:$A$49,">="&A16,تراکنش‌ها!$A$2:$A$49,"<"&EDATE(A16,1)) -> 5300 | C16: =SUMIFS(تراکنش‌ها!$E$2:$E$49,تراکنش‌ها!$B$2:$B$49,"Expense",تراکنش‌ها!$A$2:$A$49,">="&A16,تراکنش‌ها!$A$2:$A$49,"<"&EDATE(A16,1)) -> 2095
A17: 46235 | B17: =SUMIFS(تراکنش‌ها!$E$2:$E$49,تراکنش‌ها!$B$2:$B$49,"Income",تراکنش‌ها!$A$2:$A$49,">="&A17,تراکنش‌ها!$A$2:$A$49,"<"&EDATE(A17,1)) -> 8850 | C17: =SUMIFS(تراکنش‌ها!$E$2:$E$49,تراکنش‌ها!$B$2:$B$49,"Expense",تراکنش‌ها!$A$2:$A$49,">="&A17,تراکنش‌ها!$A$2:$A$49,"<"&EDATE(A17,1)) -> 1905
A18: 46266 | B18: =SUMIFS(تراکنش‌ها!$E$2:$E$49,تراکنش‌ها!$B$2:$B$49,"Income",تراکنش‌ها!$A$2:$A$49,">="&A18,تراکنش‌ها!$A$2:$A$49,"<"&EDATE(A18,1)) -> 3550 | C18: =SUMIFS(تراکنش‌ها!$E$2:$E$49,تراکنش‌ها!$B$2:$B$49,"Expense",تراکنش‌ها!$A$2:$A$49,">="&A18,تراکنش‌ها!$A$2:$A$49,"<"&EDATE(A18,1)) -> 2380
A19: 46296 | B19: =SUMIFS(تراکنش‌ها!$E$2:$E$49,تراکنش‌ها!$B$2:$B$49,"Income",تراکنش‌ها!$A$2:$A$49,">="&A19,تراکنش‌ها!$A$2:$A$49,"<"&EDATE(A19,1)) -> 7800 | C19: =SUMIFS(تراکنش‌ها!$E$2:$E$49,تراکنش‌ها!$B$2:$B$49,"Expense",تراکنش‌ها!$A$2:$A$49,">="&A19,تراکنش‌ها!$A$2:$A$49,"<"&EDATE(A19,1)) -> 1430
A20: 46327 | B20: =SUMIFS(تراکنش‌ها!$E$2:$E$49,تراکنش‌ها!$B$2:$B$49,"Income",تراکنش‌ها!$A$2:$A$49,">="&A20,تراکنش‌ها!$A$2:$A$49,"<"&EDATE(A20,1)) -> 4250 | C20: =SUMIFS(تراکنش‌ها!$E$2:$E$49,تراکنش‌ها!$B$2:$B$49,"Expense",تراکنش‌ها!$A$2:$A$49,">="&A20,تراکنش‌ها!$A$2:$A$49,"<"&EDATE(A20,1)) -> 2665
A21: 46357 | B21: =SUMIFS(تراکنش‌ها!$E$2:$E$49,تراکنش‌ها!$B$2:$B$49,"Income",تراکنش‌ها!$A$2:$A$49,">="&A21,تراکنش‌ها!$A$2:$A$49,"<"&EDATE(A21,1)) -> 0 | C21: =SUMIFS(تراکنش‌ها!$E$2:$E$49,تراکنش‌ها!$B$2:$B$49,"Expense",تراکنش‌ها!$A$2:$A$49,">="&A21,تراکنش‌ها!$A$2:$A$49,"<"&EDATE(A21,1)) -> 0

Sheet ورود داده
A1: ورود تراکنش مالی
A4: تاریخ | B4: نوع | C4: دسته‌بندی | D4: شرح | E4: مبلغ

Sheet راهنما
A1: راهنمای داشبورد مالی HMexcelpro
A4: هدف | B4: نمونه‌کار حرفه‌ای Excel برای تحلیل درآمد، هزینه، سود و بودجه.
A5: تراکنش‌ها | B5: اطلاعات درآمد و هزینه در این بخش ثبت و نگهداری می‌شود.
A6: بودجه | B6: بودجه سالانه با هزینه واقعی مقایسه می‌شود.
A7: داشبورد | B7: شاخص‌های کلیدی، روند ماهانه و مقایسه بودجه را نمایش می‌دهد.
A8: ورود داده | B8: فرم ساده برای آماده‌سازی تراکنش‌های جدید.
A9: نکته | B9: داده‌های این فایل آزمایشی و مخصوص نمونه‌کار هستند.
