Workbook

Sheet Transactions
A1: Date | B1: Type | C1: Category | D1: Description | E1: Amount | F1: Month | G1: Income | H1: Expense
A2: 46025 | B2: Income | C2: Product Sales | D2: Product Sales - Jan | E2: 4787 | F2: =TEXT(A2,"mmm") -> Jan | G2: =IF(B2="Income",E2,0) -> 4787 | H2: =IF(B2="Expense",E2,0) -> 0
A3: 46032 | B3: Income | C3: Consulting | D3: Consulting - Jan | E3: 3438 | F3: =TEXT(A3,"mmm") -> Jan | G3: =IF(B3="Income",E3,0) -> 3438 | H3: =IF(B3="Expense",E3,0) -> 0
A4: 46039 | B4: Income | C4: Online Services | D4: Online Services - Jan | E4: 4257 | F4: =TEXT(A4,"mmm") -> Jan | G4: =IF(B4="Income",E4,0) -> 4257 | H4: =IF(B4="Expense",E4,0) -> 0
A5: 46027 | B5: Expense | C5: Marketing | D5: Marketing - Jan | E5: 893 | F5: =TEXT(A5,"mmm") -> Jan | G5: =IF(B5="Income",E5,0) -> 0 | H5: =IF(B5="Expense",E5,0) -> 893
A6: 46030 | B6: Expense | C6: Software | D6: Software - Jan | E6: 461 | F6: =TEXT(A6,"mmm") -> Jan | G6: =IF(B6="Income",E6,0) -> 0 | H6: =IF(B6="Expense",E6,0) -> 461
A7: 46033 | B7: Expense | C7: Office | D7: Office - Jan | E7: 285 | F7: =TEXT(A7,"mmm") -> Jan | G7: =IF(B7="Income",E7,0) -> 0 | H7: =IF(B7="Expense",E7,0) -> 285
A8: 46036 | B8: Expense | C8: Logistics | D8: Logistics - Jan | E8: 649 | F8: =TEXT(A8,"mmm") -> Jan | G8: =IF(B8="Income",E8,0) -> 0 | H8: =IF(B8="Expense",E8,0) -> 649
A9: 46039 | B9: Expense | C9: Utilities | D9: Utilities - Jan | E9: 366 | F9: =TEXT(A9,"mmm") -> Jan | G9: =IF(B9="Income",E9,0) -> 0 | H9: =IF(B9="Expense",E9,0) -> 366
A10: 46042 | B10: Expense | C10: Payroll | D10: Payroll - Jan | E10: 2343 | F10: =TEXT(A10,"mmm") -> Jan | G10: =IF(B10="Income",E10,0) -> 0 | H10: =IF(B10="Expense",E10,0) -> 2343
A11: 46056 | B11: Income | C11: Product Sales | D11: Product Sales - Feb | E11: 4732 | F11: =TEXT(A11,"mmm") -> Feb | G11: =IF(B11="Income",E11,0) -> 4732 | H11: =IF(B11="Expense",E11,0) -> 0
A12: 46063 | B12: Income | C12: Consulting | D12: Consulting - Feb | E12: 2315 | F12: =TEXT(A12,"mmm") -> Feb | G12: =IF(B12="Income",E12,0) -> 2315 | H12: =IF(B12="Expense",E12,0) -> 0
A13: 46070 | B13: Income | C13: Online Services | D13: Online Services - Feb | E13: 4831 | F13: =TEXT(A13,"mmm") -> Feb | G13: =IF(B13="Income",E13,0) -> 4831 | H13: =IF(B13="Expense",E13,0) -> 0
... A109: 46376 | B109: Expense | C109: Payroll | D109: Payroll - Dec | E109: 2420 | F109: =TEXT(A109,"mmm") -> Dec | G109: =IF(B109="Income",E109,0) -> 0 | H109: =IF(B109="Expense",E109,0) -> 2420

Sheet Budget
A1: Category | B1: Jan | C1: Feb | D1: Mar | E1: Apr | F1: May | G1: Jun | H1: Jul | I1: Aug | J1: Sep | K1: Oct | L1: Nov | M1: Dec | N1: Annual Budget
A2: Marketing | B2: 1100 | C2: 1150 | D2: 1200 | E2: 1100 | F2: 1150 | G2: 1200 | H2: 1100 | I2: 1150 | J2: 1200 | K2: 1100 | L2: 1150 | M2: 1200 | N2: 13800
A3: Software | B3: 600 | C3: 650 | D3: 700 | E3: 600 | F3: 650 | G3: 700 | H3: 600 | I3: 650 | J3: 700 | K3: 600 | L3: 650 | M3: 700 | N3: 7800
A4: Office | B4: 450 | C4: 500 | D4: 550 | E4: 450 | F4: 500 | G4: 550 | H4: 450 | I4: 500 | J4: 550 | K4: 450 | L4: 500 | M4: 550 | N4: 6000
A5: Logistics | B5: 850 | C5: 900 | D5: 950 | E5: 850 | F5: 900 | G5: 950 | H5: 850 | I5: 900 | J5: 950 | K5: 850 | L5: 900 | M5: 950 | N5: 10800
A6: Utilities | B6: 500 | C6: 550 | D6: 600 | E6: 500 | F6: 550 | G6: 600 | H6: 500 | I6: 550 | J6: 600 | K6: 500 | L6: 550 | M6: 600 | N6: 6600
A7: Payroll | B7: 2600 | C7: 2650 | D7: 2700 | E7: 2600 | F7: 2650 | G7: 2700 | H7: 2600 | I7: 2650 | J7: 2700 | K7: 2600 | L7: 2650 | M7: 2700 | N7: 31800

Sheet Financial Dashboard
A1: HMEXCELPRO | FINANCIAL & EXPENSE DASHBOARD | R1: Month | S1: Income | T1: Expense | V1: Category | W1: Expense | Y1: Category | Z1: Actual | AA1: Budget
R2: Jan | S2: =SUMIF(Transactions!F$2:F$109,R2,Transactions!G$2:G$109) -> 12482 | T2: =SUMIF(Transactions!F$2:F$109,R2,Transactions!H$2:H$109) -> 4997 | V2: Marketing | W2: =SUMIF(Transactions!C$2:C$109,V2,Transactions!H$2:H$109) -> 13647 | Y2: Marketing | Z2: =SUMIF(Transactions!C$2:C$109,Y2,Transactions!H$2:H$109) -> 13647 | AA2: =INDEX(Budget!N$2:N$7,MATCH(Y2,Budget!A$2:A$7,0)) -> 13800
A3: Cash Flow • Expense Analysis • Budget Control • Profitability | R3: Feb | S3: =SUMIF(Transactions!F$2:F$109,R3,Transactions!G$2:G$109) -> 11878 | T3: =SUMIF(Transactions!F$2:F$109,R3,Transactions!H$2:H$109) -> 6052 | V3: Software | W3: =SUMIF(Transactions!C$2:C$109,V3,Transactions!H$2:H$109) -> 8692 | Y3: Software | Z3: =SUMIF(Transactions!C$2:C$109,Y3,Transactions!H$2:H$109) -> 8692 | AA3: =INDEX(Budget!N$2:N$7,MATCH(Y3,Budget!A$2:A$7,0)) -> 7800
R4: Mar | S4: =SUMIF(Transactions!F$2:F$109,R4,Transactions!G$2:G$109) -> 11026 | T4: =SUMIF(Transactions!F$2:F$109,R4,Transactions!H$2:H$109) -> 5869 | V4: Office | W4: =SUMIF(Transactions!C$2:C$109,V4,Transactions!H$2:H$109) -> 7064 | Y4: Office | Z4: =SUMIF(Transactions!C$2:C$109,Y4,Transactions!H$2:H$109) -> 7064 | AA4: =INDEX(Budget!N$2:N$7,MATCH(Y4,Budget!A$2:A$7,0)) -> 6000
A5: TOTAL INCOME | D5: TOTAL EXPENSE | G5: NET PROFIT | J5: PROFIT MARGIN | M5: ANNUAL BUDGET | R5: Apr | S5: =SUMIF(Transactions!F$2:F$109,R5,Transactions!G$2:G$109) -> 11059 | T5: =SUMIF(Transactions!F$2:F$109,R5,Transactions!H$2:H$109) -> 6336 | V5: Logistics | W5: =SUMIF(Transactions!C$2:C$109,V5,Transactions!H$2:H$109) -> 11402 | Y5: Logistics | Z5: =SUMIF(Transactions!C$2:C$109,Y5,Transactions!H$2:H$109) -> 11402 | AA5: =INDEX(Budget!N$2:N$7,MATCH(Y5,Budget!A$2:A$7,0)) -> 10800
A6: =SUM(Transactions!G2:G109) -> 145235 | D6: =SUM(Transactions!H2:H109) -> 75147 | G6: =SUM(Transactions!G2:G109)-SUM(Transactions!H2:H109) -> 70088 | J6: =IFERROR((SUM(Transactions!G2:G109)-SUM(Transactions!H2:H109))/SUM(Transactions!G2:G109),0) -> 0.4825834 | M6: =SUM(Budget!N2:N7) -> 76800 | R6: May | S6: =SUMIF(Transactions!F$2:F$109,R6,Transactions!G$2:G$109) -> 12727 | T6: =SUMIF(Transactions!F$2:F$109,R6,Transactions!H$2:H$109) -> 6129 | V6: Utilities | W6: =SUMIF(Transactions!C$2:C$109,V6,Transactions!H$2:H$109) -> 6352 | Y6: Utilities | Z6: =SUMIF(Transactions!C$2:C$109,Y6,Transactions!H$2:H$109) -> 6352 | AA6: =INDEX(Budget!N$2:N$7,MATCH(Y6,Budget!A$2:A$7,0)) -> 6600
R7: Jun | S7: =SUMIF(Transactions!F$2:F$109,R7,Transactions!G$2:G$109) -> 10435 | T7: =SUMIF(Transactions!F$2:F$109,R7,Transactions!H$2:H$109) -> 6220 | V7: Payroll | W7: =SUMIF(Transactions!C$2:C$109,V7,Transactions!H$2:H$109) -> 27990 | Y7: Payroll | Z7: =SUMIF(Transactions!C$2:C$109,Y7,Transactions!H$2:H$109) -> 27990 | AA7: =INDEX(Budget!N$2:N$7,MATCH(Y7,Budget!A$2:A$7,0)) -> 31800
R8: Jul | S8: =SUMIF(Transactions!F$2:F$109,R8,Transactions!G$2:G$109) -> 12596 | T8: =SUMIF(Transactions!F$2:F$109,R8,Transactions!H$2:H$109) -> 5913
R9: Aug | S9: =SUMIF(Transactions!F$2:F$109,R9,Transactions!G$2:G$109) -> 14333 | T9: =SUMIF(Transactions!F$2:F$109,R9,Transactions!H$2:H$109) -> 6712
A10: MONTHLY CASH FLOW | I10: EXPENSE BREAKDOWN | R10: Sep | S10: =SUMIF(Transactions!F$2:F$109,R10,Transactions!G$2:G$109) -> 12264 | T10: =SUMIF(Transactions!F$2:F$109,R10,Transactions!H$2:H$109) -> 6548
R11: Oct | S11: =SUMIF(Transactions!F$2:F$109,R11,Transactions!G$2:G$109) -> 11378 | T11: =SUMIF(Transactions!F$2:F$109,R11,Transactions!H$2:H$109) -> 6724
R12: Nov | S12: =SUMIF(Transactions!F$2:F$109,R12,Transactions!G$2:G$109) -> 12926 | T12: =SUMIF(Transactions!F$2:F$109,R12,Transactions!H$2:H$109) -> 6732
R13: Dec | S13: =SUMIF(Transactions!F$2:F$109,R13,Transactions!G$2:G$109) -> 12131 | T13: =SUMIF(Transactions!F$2:F$109,R13,Transactions!H$2:H$109) -> 6915
A27: BUDGET VS ACTUAL | I27: FINANCIAL INSIGHTS
I28: TOP EXPENSE CATEGORY | M28: BEST CASH FLOW MONTH
I29: =INDEX(V2:V7,MATCH(MAX(W2:W7),W2:W7,0)) -> Payroll | M29: =INDEX(R2:R13,MATCH(MAX(S2:S13-T2:T13),S2:S13-T2:T13,0)) -> #VALUE!
I32: AVG MONTHLY EXPENSE | M32: BUDGET UTILIZATION
I33: =AVERAGE(T2:T13) -> 6262.25 | M33: =IFERROR(SUM(W2:W7)/SUM(AA2:AA7),0) -> 0.97847656
A44: HMexcelpro | Excel • Financial Analysis • Dashboards • Business Reporting

Sheet Data Entry
A1: HMEXCELPRO | FINANCIAL DATA ENTRY
A4: Date | B4: Type | C4: Category | D4: Description | E4: Amount | F4: Review Status

Sheet Instructions
A1: HMEXCELPRO FINANCIAL DASHBOARD — PORTFOLIO PROJECT
A4: A professional Excel portfolio project for income/expense tracking, cash-flow analysis, budget control and management reporting.
A7: HOW TO USE
A8: 1 | B8: Add transactions to the Transactions sheet or prepare them in Data Entry.
A9: 2 | B9: Set monthly category budgets in the Budget sheet.
A10: 3 | B10: Review KPIs and charts in Financial Dashboard.
A11: 4 | B11: Use expense breakdown and Budget vs Actual to identify cost pressure.
A13: PORTFOLIO SKILLS DEMONSTRATED
A14: • | B14: Excel formulas, structured data, conditional formatting and validation.
A15: • | B15: Financial analysis, expense reporting, cash-flow visualization and dashboard design.
